fitur/__init__.py
fitur/cmdlist.py
adjidev_cbs-1.0.1.dist-info/LICENSE
adjidev_cbs-1.0.1.dist-info/METADATA
adjidev_cbs-1.0.1.dist-info/WHEEL
adjidev_cbs-1.0.1.dist-info/entry_points.txt
adjidev_cbs-1.0.1.dist-info/top_level.txt
adjidev_cbs-1.0.1.dist-info/RECORD
