Metadata-Version: 2.1
Name: adjidev-cbs
Version: 1.0.1
Summary: Cyber brebes system advanced hacking tools
Home-page: https://github.com/adjidev/cbs
Author: Adjidev
Author-email: pixelpixx26@gmail.com
Project-URL: Bug Tracker, https://github.com/adjidev/cbs/issues
Classifier: Programming Language :: Python :: 3
Classifier: License :: OSI Approved :: MIT License
Classifier: Operating System :: OS Independent
Requires-Python: >=3.11
License-File: LICENSE
Requires-Dist: setuptools
